gravitorchdata/__init__.py
gravitorchdata/creators/__init__.py
gravitorchdata/creators/dataloader2/__init__.py
gravitorchdata/creators/dataloader2/base.py
gravitorchdata/creators/dataloader2/vanilla.py
gravitorchdata/creators/datastream/__init__.py
gravitorchdata/creators/datastream/base.py
gravitorchdata/creators/datastream/dataloader.py
gravitorchdata/creators/datastream/iterable.py
gravitorchdata/dataloaders/__init__.py
gravitorchdata/dataloaders/factory.py
gravitorchdata/datasources/__init__.py
gravitorchdata/datasources/vanilla.py
gravitorchdata/datastreams/__init__.py
gravitorchdata/datastreams/base.py
gravitorchdata/datastreams/dataloader.py
gravitorchdata/datastreams/iterable.py
gravitorchdata-0.0.1a0.dist-info/LICENSE
gravitorchdata-0.0.1a0.dist-info/METADATA
gravitorchdata-0.0.1a0.dist-info/WHEEL
gravitorchdata-0.0.1a0.dist-info/RECORD
