Metadata-Version: 2.1
Name: gravitorchdata
Version: 0.0.1a0
Summary: Plugin to use torchdata with gravitorch
Home-page: https://github.com/durandtibo/gravitorchdata
License: BSD-3-Clause
Keywords: gravitorch,pytorch,torchdata
Author: Thibaut Durand
Author-email: durand.tibo+gh@gmail.com
Requires-Python: >=3.9,<3.12
Classifier: Development Status :: 3 - Alpha
Classifier: Intended Audience :: Developers
Classifier: Intended Audience :: Information Technology
Classifier: Intended Audience :: Science/Research
Classifier: License :: OSI Approved :: BSD License
Classifier: Operating System :: POSIX :: Linux
Classifier: Programming Language :: Python :: 3
Classifier: Programming Language :: Python :: 3.9
Classifier: Programming Language :: Python :: 3.10
Classifier: Programming Language :: Python :: 3.11
Classifier: Topic :: Scientific/Engineering :: Artificial Intelligence
Provides-Extra: all
Requires-Dist: gravitorch (>=0.0.23a1,<0.0.24)
Requires-Dist: torch (>=2.0.0,<2.2.0)
Requires-Dist: torchdata (>=0.6,<0.8)
Project-URL: Repository, https://github.com/durandtibo/gravitorchdata
